HeuristAI/__init__.py
HeuristAI/example_EvolutionofHeuristics.py
HeuristAI/example_FunSearch.py
HeuristAI/example_ReEvo.py
HeuristAI/text_utils.py
HeuristAI/utils.py
HeuristAI-0.1.0.dist-info/LICENSE
HeuristAI-0.1.0.dist-info/METADATA
HeuristAI-0.1.0.dist-info/WHEEL
HeuristAI-0.1.0.dist-info/top_level.txt
HeuristAI-0.1.0.dist-info/RECORD
