Metadata-Version: 2.1
Name: HeuristAI
Version: 0.1.0
Summary: Evolve heuristics using LLM-driven Genetic Programming.
Home-page: https://github.com/m229abd/HeuristAI
Author: Mostafa Abdolmaleki
Author-email: m229abd@gmail.com
License: MIT
Classifier: Programming Language :: Python :: 3
Classifier: License :: OSI Approved :: MIT License
Requires-Python: >=3.7
License-File: LICENSE
Requires-Dist: ray
Requires-Dist: langchain
Requires-Dist: langchain-openai
Requires-Dist: pydantic
